[
	{
		"pkg": "@capacitor-community/http",
		"classpath": "com.getcapacitor.plugin.http.Http"
	},
	{
		"pkg": "@capacitor/app",
		"classpath": "com.capacitorjs.plugins.app.AppPlugin"
	},
	{
		"pkg": "@capacitor/app-launcher",
		"classpath": "com.capacitorjs.plugins.applauncher.AppLauncherPlugin"
	},
	{
		"pkg": "@capacitor/browser",
		"classpath": "com.capacitorjs.plugins.browser.BrowserPlugin"
	},
	{
		"pkg": "@capacitor/device",
		"classpath": "com.capacitorjs.plugins.device.DevicePlugin"
	},
	{
		"pkg": "@capacitor/filesystem",
		"classpath": "com.capacitorjs.plugins.filesystem.FilesystemPlugin"
	},
	{
		"pkg": "@capacitor/geolocation",
		"classpath": "com.capacitorjs.plugins.geolocation.GeolocationPlugin"
	},
	{
		"pkg": "@capacitor/haptics",
		"classpath": "com.capacitorjs.plugins.haptics.HapticsPlugin"
	},
	{
		"pkg": "@capacitor/keyboard",
		"classpath": "com.capacitorjs.plugins.keyboard.KeyboardPlugin"
	},
	{
		"pkg": "@capacitor/network",
		"classpath": "com.capacitorjs.plugins.network.NetworkPlugin"
	},
	{
		"pkg": "@capacitor/share",
		"classpath": "com.capacitorjs.plugins.share.SharePlugin"
	},
	{
		"pkg": "@capacitor/splash-screen",
		"classpath": "com.capacitorjs.plugins.splashscreen.SplashScreenPlugin"
	},
	{
		"pkg": "@capacitor/storage",
		"classpath": "com.capacitorjs.plugins.storage.StoragePlugin"
	},
	{
		"pkg": "@proteansoftware/capacitor-start-navigation",
		"classpath": "com.servicesight.capacitor.startnavigation.StartNavigationPlugin"
	}
]
